cipherforge/__init__.py
cipherforge/cipherforge.py
cipherforge-1.0.dist-info/licenses/LICENSE
cipherforge-1.0.dist-info/METADATA
cipherforge-1.0.dist-info/WHEEL
cipherforge-1.0.dist-info/entry_points.txt
cipherforge-1.0.dist-info/top_level.txt
cipherforge-1.0.dist-info/RECORD
