Metadata-Version: 2.4
Name: cipherforge
Version: 1.0
Summary: Secure file encryption tool for all file types
Author-email: gtk-gg <your-email@example.com>
License: MIT
Project-URL: Homepage, https://github.com/gtk-gg/cipherforge
Project-URL: Repository, https://github.com/gtk-gg/cipherforge
Project-URL: Issue Tracker, https://github.com/gtk-gg/cipherforge/issues
Keywords: encryption,security,cryptography,file-encryption,privacy
Classifier: Development Status :: 4 - Beta
Classifier: Intended Audience :: End Users/Desktop
Classifier: Topic :: Security :: Cryptography
Classifier: License :: OSI Approved :: MIT License
Classifier: Programming Language :: Python :: 3
Classifier: Programming Language :: Python :: 3.8
Classifier: Programming Language :: Python :: 3.9
Classifier: Programming Language :: Python :: 3.10
Classifier: Programming Language :: Python :: 3.11
Classifier: Programming Language :: Python :: 3.12
Classifier: Operating System :: OS Independent
Requires-Python: >=3.8
License-File: LICENSE
Requires-Dist: cryptography>=41.0.0
Requires-Dist: pyperclip>=1.8.0
Provides-Extra: dev
Requires-Dist: twine; extra == "dev"
Requires-Dist: setuptools; extra == "dev"
Requires-Dist: wheel; extra == "dev"
Dynamic: license-file
